[
  {
    "icon": "ghost",
    "topic": "Twenty Tales of Terror",
    "subtopic": "Feast your eyes on the exclusive reviews of the infamous Edgar J Hyde 'Creepers'"
  },
  {
    "icon": "alien",
    "topic": "Two Authors",
    "subtopic": "A chilling alliance of two souls drawn together by their love for horror"
  },
  {
    "icon": "books",
    "topic": "Bilingual Commitment",
    "subtopic": "To grasp the true horror, we ventured into both English and Portuguese editions"
  },
  {
    "icon": "cross",
    "topic": "A Dec of Darkness",
    "subtopic": "In the ominous year of 2015, fate intertwined, setting the sinister stage for this collaboration"
  }
]
